[
  {
    "segment_id": "S00001",
    "transport_relevant": false
  },
  {
    "segment_id": "S00002",
    "transport_relevant": false
  },
  {
    "segment_id": "S00003",
    "transport_relevant": false
  },
  {
    "segment_id": "S00004",
    "transport_relevant": false
  },
  {
    "segment_id": "S00005",
    "transport_relevant": false
  },
  {
    "segment_id": "S00006",
    "transport_relevant": false
  },
  {
    "segment_id": "S00007",
    "transport_relevant": false
  },
  {
    "segment_id": "S00008",
    "transport_relevant": false
  },
  {
    "segment_id": "S00009",
    "transport_relevant": false
  },
  {
    "segment_id": "S00010",
    "transport_relevant": false
  },
  {
    "segment_id": "S00011",
    "transport_relevant": false
  },
  {
    "segment_id": "S00012",
    "transport_relevant": false
  },
  {
    "segment_id": "S00013",
    "transport_relevant": false
  },
  {
    "segment_id": "S00014",
    "transport_relevant": false
  },
  {
    "segment_id": "S00015",
    "transport_relevant": false
  },
  {
    "segment_id": "S00016",
    "transport_relevant": false
  },
  {
    "segment_id": "S00017",
    "transport_relevant": false
  },
  {
    "segment_id": "S00018",
    "transport_relevant": false
  },
  {
    "segment_id": "S00019",
    "transport_relevant": false
  },
  {
    "segment_id": "S00020",
    "transport_relevant": false
  },
  {
    "segment_id": "S00021",
    "transport_relevant": false
  },
  {
    "segment_id": "S00022",
    "transport_relevant": false
  },
  {
    "segment_id": "S00023",
    "transport_relevant": false
  },
  {
    "segment_id": "S00024",
    "transport_relevant": false
  },
  {
    "segment_id": "S00025",
    "transport_relevant": false
  },
  {
    "segment_id": "S00026",
    "transport_relevant": false
  },
  {
    "segment_id": "S00027",
    "transport_relevant": false
  },
  {
    "segment_id": "S00028",
    "transport_relevant": false
  },
  {
    "segment_id": "S00029",
    "transport_relevant": false
  },
  {
    "segment_id": "S00030",
    "transport_relevant": false
  },
  {
    "segment_id": "S00031",
    "transport_relevant": false
  },
  {
    "segment_id": "S00032",
    "transport_relevant": false
  },
  {
    "segment_id": "S00033",
    "transport_relevant": false
  },
  {
    "segment_id": "S00034",
    "transport_relevant": false
  },
  {
    "segment_id": "S00035",
    "transport_relevant": false
  },
  {
    "segment_id": "S00036",
    "transport_relevant": false
  },
  {
    "segment_id": "S00037",
    "transport_relevant": false
  },
  {
    "segment_id": "S00038",
    "transport_relevant": false
  },
  {
    "segment_id": "S00039",
    "transport_relevant": false
  },
  {
    "segment_id": "S00040",
    "transport_relevant": false
  },
  {
    "segment_id": "S00041",
    "transport_relevant": false
  },
  {
    "segment_id": "S00042",
    "transport_relevant": false
  },
  {
    "segment_id": "S00043",
    "transport_relevant": false
  },
  {
    "segment_id": "S00044",
    "transport_relevant": false
  },
  {
    "segment_id": "S00045",
    "transport_relevant": false
  },
  {
    "segment_id": "S00046",
    "transport_relevant": false
  },
  {
    "segment_id": "S00047",
    "transport_relevant": false
  },
  {
    "segment_id": "S00048",
    "transport_relevant": false
  },
  {
    "segment_id": "S00049",
    "transport_relevant": true
  },
  {
    "segment_id": "S00050",
    "transport_relevant": false
  },
  {
    "segment_id": "S00051",
    "transport_relevant": false
  },
  {
    "segment_id": "S00052",
    "transport_relevant": false
  },
  {
    "segment_id": "S00053",
    "transport_relevant": false
  },
  {
    "segment_id": "S00054",
    "transport_relevant": false
  },
  {
    "segment_id": "S00055",
    "transport_relevant": false
  },
  {
    "segment_id": "S00056",
    "transport_relevant": false
  },
  {
    "segment_id": "S00057",
    "transport_relevant": false
  },
  {
    "segment_id": "S00058",
    "transport_relevant": false
  },
  {
    "segment_id": "S00059",
    "transport_relevant": false
  },
  {
    "segment_id": "S00060",
    "transport_relevant": false
  },
  {
    "segment_id": "S00061",
    "transport_relevant": false
  },
  {
    "segment_id": "S00062",
    "transport_relevant": false
  },
  {
    "segment_id": "S00063",
    "transport_relevant": false
  },
  {
    "segment_id": "S00064",
    "transport_relevant": false
  },
  {
    "segment_id": "S00065",
    "transport_relevant": false
  },
  {
    "segment_id": "S00066",
    "transport_relevant": false
  },
  {
    "segment_id": "S00067",
    "transport_relevant": false
  },
  {
    "segment_id": "S00068",
    "transport_relevant": false
  },
  {
    "segment_id": "S00069",
    "transport_relevant": false
  },
  {
    "segment_id": "S00070",
    "transport_relevant": false
  },
  {
    "segment_id": "S00071",
    "transport_relevant": false
  },
  {
    "segment_id": "S00072",
    "transport_relevant": false
  },
  {
    "segment_id": "S00073",
    "transport_relevant": false
  },
  {
    "segment_id": "S00074",
    "transport_relevant": false
  },
  {
    "segment_id": "S00075",
    "transport_relevant": false
  },
  {
    "segment_id": "S00076",
    "transport_relevant": false
  },
  {
    "segment_id": "S00077",
    "transport_relevant": false
  },
  {
    "segment_id": "S00078",
    "transport_relevant": false
  },
  {
    "segment_id": "S00079",
    "transport_relevant": true
  },
  {
    "segment_id": "S00080",
    "transport_relevant": false
  },
  {
    "segment_id": "S00081",
    "transport_relevant": false
  },
  {
    "segment_id": "S00082",
    "transport_relevant": false
  },
  {
    "segment_id": "S00083",
    "transport_relevant": false
  },
  {
    "segment_id": "S00084",
    "transport_relevant": false
  },
  {
    "segment_id": "S00085",
    "transport_relevant": false
  },
  {
    "segment_id": "S00086",
    "transport_relevant": false
  },
  {
    "segment_id": "S00087",
    "transport_relevant": false
  },
  {
    "segment_id": "S00088",
    "transport_relevant": false
  },
  {
    "segment_id": "S00089",
    "transport_relevant": false
  },
  {
    "segment_id": "S00090",
    "transport_relevant": false
  },
  {
    "segment_id": "S00091",
    "transport_relevant": false
  },
  {
    "segment_id": "S00092",
    "transport_relevant": false
  },
  {
    "segment_id": "S00093",
    "transport_relevant": false
  },
  {
    "segment_id": "S00094",
    "transport_relevant": true
  },
  {
    "segment_id": "S00095",
    "transport_relevant": false
  },
  {
    "segment_id": "S00096",
    "transport_relevant": true
  },
  {
    "segment_id": "S00097",
    "transport_relevant": false
  },
  {
    "segment_id": "S00098",
    "transport_relevant": false
  },
  {
    "segment_id": "S00099",
    "transport_relevant": false
  },
  {
    "segment_id": "S00100",
    "transport_relevant": true
  },
  {
    "segment_id": "S00101",
    "transport_relevant": false
  },
  {
    "segment_id": "S00102",
    "transport_relevant": true
  },
  {
    "segment_id": "S00103",
    "transport_relevant": true
  },
  {
    "segment_id": "S00104",
    "transport_relevant": true
  },
  {
    "segment_id": "S00105",
    "transport_relevant": true
  },
  {
    "segment_id": "S00106",
    "transport_relevant": true
  },
  {
    "segment_id": "S00107",
    "transport_relevant": false
  },
  {
    "segment_id": "S00108",
    "transport_relevant": false
  },
  {
    "segment_id": "S00109",
    "transport_relevant": false
  },
  {
    "segment_id": "S00110",
    "transport_relevant": false
  },
  {
    "segment_id": "S00111",
    "transport_relevant": false
  },
  {
    "segment_id": "S00112",
    "transport_relevant": false
  },
  {
    "segment_id": "S00113",
    "transport_relevant": false
  },
  {
    "segment_id": "S00114",
    "transport_relevant": false
  },
  {
    "segment_id": "S00115",
    "transport_relevant": false
  },
  {
    "segment_id": "S00116",
    "transport_relevant": false
  },
  {
    "segment_id": "S00117",
    "transport_relevant": false
  },
  {
    "segment_id": "S00118",
    "transport_relevant": true
  },
  {
    "segment_id": "S00119",
    "transport_relevant": false
  },
  {
    "segment_id": "S00120",
    "transport_relevant": false
  },
  {
    "segment_id": "S00121",
    "transport_relevant": false
  },
  {
    "segment_id": "S00122",
    "transport_relevant": false
  },
  {
    "segment_id": "S00123",
    "transport_relevant": false
  },
  {
    "segment_id": "S00124",
    "transport_relevant": false
  },
  {
    "segment_id": "S00125",
    "transport_relevant": false
  },
  {
    "segment_id": "S00126",
    "transport_relevant": false
  },
  {
    "segment_id": "S00127",
    "transport_relevant": false
  },
  {
    "segment_id": "S00128",
    "transport_relevant": false
  },
  {
    "segment_id": "S00129",
    "transport_relevant": false
  },
  {
    "segment_id": "S00130",
    "transport_relevant": false
  },
  {
    "segment_id": "S00131",
    "transport_relevant": false
  },
  {
    "segment_id": "S00132",
    "transport_relevant": false
  },
  {
    "segment_id": "S00133",
    "transport_relevant": false
  },
  {
    "segment_id": "S00134",
    "transport_relevant": false
  },
  {
    "segment_id": "S00135",
    "transport_relevant": false
  },
  {
    "segment_id": "S00136",
    "transport_relevant": false
  },
  {
    "segment_id": "S00137",
    "transport_relevant": false
  },
  {
    "segment_id": "S00138",
    "transport_relevant": false
  },
  {
    "segment_id": "S00139",
    "transport_relevant": false
  },
  {
    "segment_id": "S00140",
    "transport_relevant": false
  },
  {
    "segment_id": "S00141",
    "transport_relevant": false
  },
  {
    "segment_id": "S00142",
    "transport_relevant": false
  },
  {
    "segment_id": "S00143",
    "transport_relevant": false
  },
  {
    "segment_id": "S00144",
    "transport_relevant": false
  },
  {
    "segment_id": "S00145",
    "transport_relevant": false
  },
  {
    "segment_id": "S00146",
    "transport_relevant": false
  },
  {
    "segment_id": "S00147",
    "transport_relevant": false
  },
  {
    "segment_id": "S00148",
    "transport_relevant": false
  },
  {
    "segment_id": "S00149",
    "transport_relevant": false
  },
  {
    "segment_id": "S00150",
    "transport_relevant": false
  },
  {
    "segment_id": "S00151",
    "transport_relevant": true
  },
  {
    "segment_id": "S00152",
    "transport_relevant": true
  },
  {
    "segment_id": "S00153",
    "transport_relevant": true
  },
  {
    "segment_id": "S00154",
    "transport_relevant": true
  },
  {
    "segment_id": "S00155",
    "transport_relevant": false
  },
  {
    "segment_id": "S00156",
    "transport_relevant": false
  },
  {
    "segment_id": "S00157",
    "transport_relevant": true
  },
  {
    "segment_id": "S00158",
    "transport_relevant": false
  },
  {
    "segment_id": "S00159",
    "transport_relevant": false
  },
  {
    "segment_id": "S00160",
    "transport_relevant": false
  },
  {
    "segment_id": "S00161",
    "transport_relevant": false
  },
  {
    "segment_id": "S00162",
    "transport_relevant": false
  },
  {
    "segment_id": "S00163",
    "transport_relevant": false
  },
  {
    "segment_id": "S00164",
    "transport_relevant": false
  },
  {
    "segment_id": "S00165",
    "transport_relevant": false
  },
  {
    "segment_id": "S00166",
    "transport_relevant": false
  },
  {
    "segment_id": "S00167",
    "transport_relevant": false
  },
  {
    "segment_id": "S00168",
    "transport_relevant": false
  },
  {
    "segment_id": "S00169",
    "transport_relevant": false
  },
  {
    "segment_id": "S00170",
    "transport_relevant": false
  },
  {
    "segment_id": "S00171",
    "transport_relevant": false
  },
  {
    "segment_id": "S00172",
    "transport_relevant": false
  },
  {
    "segment_id": "S00173",
    "transport_relevant": false
  },
  {
    "segment_id": "S00174",
    "transport_relevant": false
  },
  {
    "segment_id": "S00175",
    "transport_relevant": false
  },
  {
    "segment_id": "S00176",
    "transport_relevant": false
  },
  {
    "segment_id": "S00177",
    "transport_relevant": false
  },
  {
    "segment_id": "S00178",
    "transport_relevant": false
  },
  {
    "segment_id": "S00179",
    "transport_relevant": false
  },
  {
    "segment_id": "S00180",
    "transport_relevant": false
  },
  {
    "segment_id": "S00181",
    "transport_relevant": false
  },
  {
    "segment_id": "S00182",
    "transport_relevant": false
  },
  {
    "segment_id": "S00183",
    "transport_relevant": false
  },
  {
    "segment_id": "S00184",
    "transport_relevant": true
  },
  {
    "segment_id": "S00185",
    "transport_relevant": false
  },
  {
    "segment_id": "S00186",
    "transport_relevant": false
  },
  {
    "segment_id": "S00187",
    "transport_relevant": false
  },
  {
    "segment_id": "S00188",
    "transport_relevant": false
  },
  {
    "segment_id": "S00189",
    "transport_relevant": false
  },
  {
    "segment_id": "S00190",
    "transport_relevant": false
  },
  {
    "segment_id": "S00191",
    "transport_relevant": false
  },
  {
    "segment_id": "S00192",
    "transport_relevant": false
  },
  {
    "segment_id": "S00193",
    "transport_relevant": false
  },
  {
    "segment_id": "S00194",
    "transport_relevant": false
  },
  {
    "segment_id": "S00195",
    "transport_relevant": false
  },
  {
    "segment_id": "S00196",
    "transport_relevant": false
  },
  {
    "segment_id": "S00197",
    "transport_relevant": false
  },
  {
    "segment_id": "S00198",
    "transport_relevant": false
  },
  {
    "segment_id": "S00199",
    "transport_relevant": false
  },
  {
    "segment_id": "S00200",
    "transport_relevant": false
  },
  {
    "segment_id": "S00201",
    "transport_relevant": false
  },
  {
    "segment_id": "S00202",
    "transport_relevant": false
  },
  {
    "segment_id": "S00203",
    "transport_relevant": false
  },
  {
    "segment_id": "S00204",
    "transport_relevant": false
  },
  {
    "segment_id": "S00205",
    "transport_relevant": false
  },
  {
    "segment_id": "S00206",
    "transport_relevant": false
  },
  {
    "segment_id": "S00207",
    "transport_relevant": false
  },
  {
    "segment_id": "S00208",
    "transport_relevant": false
  },
  {
    "segment_id": "S00209",
    "transport_relevant": false
  },
  {
    "segment_id": "S00210",
    "transport_relevant": false
  },
  {
    "segment_id": "S00211",
    "transport_relevant": false
  },
  {
    "segment_id": "S00212",
    "transport_relevant": false
  },
  {
    "segment_id": "S00213",
    "transport_relevant": false
  },
  {
    "segment_id": "S00214",
    "transport_relevant": false
  },
  {
    "segment_id": "S00215",
    "transport_relevant": false
  },
  {
    "segment_id": "S00216",
    "transport_relevant": false
  },
  {
    "segment_id": "S00217",
    "transport_relevant": false
  },
  {
    "segment_id": "S00218",
    "transport_relevant": true
  },
  {
    "segment_id": "S00219",
    "transport_relevant": true
  },
  {
    "segment_id": "S00220",
    "transport_relevant": true
  },
  {
    "segment_id": "S00221",
    "transport_relevant": true
  },
  {
    "segment_id": "S00222",
    "transport_relevant": false
  },
  {
    "segment_id": "S00223",
    "transport_relevant": true
  },
  {
    "segment_id": "S00224",
    "transport_relevant": false
  },
  {
    "segment_id": "S00225",
    "transport_relevant": false
  },
  {
    "segment_id": "S00226",
    "transport_relevant": false
  },
  {
    "segment_id": "S00227",
    "transport_relevant": false
  },
  {
    "segment_id": "S00228",
    "transport_relevant": false
  },
  {
    "segment_id": "S00229",
    "transport_relevant": false
  },
  {
    "segment_id": "S00230",
    "transport_relevant": false
  },
  {
    "segment_id": "S00231",
    "transport_relevant": false
  },
  {
    "segment_id": "S00232",
    "transport_relevant": false
  },
  {
    "segment_id": "S00233",
    "transport_relevant": false
  },
  {
    "segment_id": "S00234",
    "transport_relevant": false
  },
  {
    "segment_id": "S00235",
    "transport_relevant": false
  },
  {
    "segment_id": "S00236",
    "transport_relevant": false
  },
  {
    "segment_id": "S00237",
    "transport_relevant": false
  },
  {
    "segment_id": "S00238",
    "transport_relevant": false
  },
  {
    "segment_id": "S00239",
    "transport_relevant": false
  },
  {
    "segment_id": "S00240",
    "transport_relevant": false
  },
  {
    "segment_id": "S00241",
    "transport_relevant": false
  },
  {
    "segment_id": "S00242",
    "transport_relevant": false
  },
  {
    "segment_id": "S00243",
    "transport_relevant": false
  },
  {
    "segment_id": "S00244",
    "transport_relevant": false
  },
  {
    "segment_id": "S00245",
    "transport_relevant": false
  },
  {
    "segment_id": "S00246",
    "transport_relevant": false
  },
  {
    "segment_id": "S00247",
    "transport_relevant": false
  },
  {
    "segment_id": "S00248",
    "transport_relevant": false
  },
  {
    "segment_id": "S00249",
    "transport_relevant": false
  },
  {
    "segment_id": "S00250",
    "transport_relevant": false
  },
  {
    "segment_id": "S00251",
    "transport_relevant": false
  },
  {
    "segment_id": "S00252",
    "transport_relevant": false
  },
  {
    "segment_id": "S00253",
    "transport_relevant": false
  },
  {
    "segment_id": "S00254",
    "transport_relevant": false
  },
  {
    "segment_id": "S00255",
    "transport_relevant": false
  },
  {
    "segment_id": "S00256",
    "transport_relevant": false
  },
  {
    "segment_id": "S00257",
    "transport_relevant": false
  },
  {
    "segment_id": "S00258",
    "transport_relevant": false
  },
  {
    "segment_id": "S00259",
    "transport_relevant": false
  },
  {
    "segment_id": "S00260",
    "transport_relevant": false
  },
  {
    "segment_id": "S00261",
    "transport_relevant": false
  },
  {
    "segment_id": "S00262",
    "transport_relevant": false
  },
  {
    "segment_id": "S00263",
    "transport_relevant": false
  },
  {
    "segment_id": "S00264",
    "transport_relevant": false
  },
  {
    "segment_id": "S00265",
    "transport_relevant": false
  },
  {
    "segment_id": "S00266",
    "transport_relevant": false
  },
  {
    "segment_id": "S00267",
    "transport_relevant": false
  },
  {
    "segment_id": "S00268",
    "transport_relevant": false
  },
  {
    "segment_id": "S00269",
    "transport_relevant": false
  },
  {
    "segment_id": "S00270",
    "transport_relevant": false
  },
  {
    "segment_id": "S00271",
    "transport_relevant": false
  },
  {
    "segment_id": "S00272",
    "transport_relevant": false
  },
  {
    "segment_id": "S00273",
    "transport_relevant": false
  },
  {
    "segment_id": "S00274",
    "transport_relevant": false
  },
  {
    "segment_id": "S00275",
    "transport_relevant": false
  },
  {
    "segment_id": "S00276",
    "transport_relevant": false
  },
  {
    "segment_id": "S00277",
    "transport_relevant": false
  },
  {
    "segment_id": "S00278",
    "transport_relevant": false
  },
  {
    "segment_id": "S00279",
    "transport_relevant": false
  },
  {
    "segment_id": "S00280",
    "transport_relevant": false
  },
  {
    "segment_id": "S00281",
    "transport_relevant": false
  },
  {
    "segment_id": "S00282",
    "transport_relevant": false
  },
  {
    "segment_id": "S00283",
    "transport_relevant": false
  },
  {
    "segment_id": "S00284",
    "transport_relevant": false
  },
  {
    "segment_id": "S00285",
    "transport_relevant": false
  },
  {
    "segment_id": "S00286",
    "transport_relevant": false
  },
  {
    "segment_id": "S00287",
    "transport_relevant": false
  },
  {
    "segment_id": "S00288",
    "transport_relevant": false
  },
  {
    "segment_id": "S00289",
    "transport_relevant": false
  },
  {
    "segment_id": "S00290",
    "transport_relevant": false
  },
  {
    "segment_id": "S00291",
    "transport_relevant": false
  },
  {
    "segment_id": "S00292",
    "transport_relevant": false
  },
  {
    "segment_id": "S00293",
    "transport_relevant": false
  },
  {
    "segment_id": "S00294",
    "transport_relevant": false
  },
  {
    "segment_id": "S00295",
    "transport_relevant": false
  },
  {
    "segment_id": "S00296",
    "transport_relevant": false
  },
  {
    "segment_id": "S00297",
    "transport_relevant": false
  },
  {
    "segment_id": "S00298",
    "transport_relevant": false
  },
  {
    "segment_id": "S00299",
    "transport_relevant": false
  },
  {
    "segment_id": "S00300",
    "transport_relevant": false
  },
  {
    "segment_id": "S00301",
    "transport_relevant": false
  },
  {
    "segment_id": "S00302",
    "transport_relevant": false
  },
  {
    "segment_id": "S00303",
    "transport_relevant": false
  },
  {
    "segment_id": "S00304",
    "transport_relevant": false
  },
  {
    "segment_id": "S00305",
    "transport_relevant": false
  },
  {
    "segment_id": "S00306",
    "transport_relevant": false
  },
  {
    "segment_id": "S00307",
    "transport_relevant": false
  },
  {
    "segment_id": "S00308",
    "transport_relevant": false
  },
  {
    "segment_id": "S00309",
    "transport_relevant": false
  },
  {
    "segment_id": "S00310",
    "transport_relevant": false
  },
  {
    "segment_id": "S00311",
    "transport_relevant": false
  },
  {
    "segment_id": "S00312",
    "transport_relevant": false
  },
  {
    "segment_id": "S00313",
    "transport_relevant": false
  },
  {
    "segment_id": "S00314",
    "transport_relevant": false
  },
  {
    "segment_id": "S00315",
    "transport_relevant": false
  },
  {
    "segment_id": "S00316",
    "transport_relevant": false
  },
  {
    "segment_id": "S00317",
    "transport_relevant": true
  },
  {
    "segment_id": "S00318",
    "transport_relevant": false
  },
  {
    "segment_id": "S00319",
    "transport_relevant": false
  },
  {
    "segment_id": "S00320",
    "transport_relevant": false
  },
  {
    "segment_id": "S00321",
    "transport_relevant": true
  },
  {
    "segment_id": "S00322",
    "transport_relevant": false
  },
  {
    "segment_id": "S00323",
    "transport_relevant": false
  },
  {
    "segment_id": "S00324",
    "transport_relevant": false
  },
  {
    "segment_id": "S00325",
    "transport_relevant": false
  },
  {
    "segment_id": "S00326",
    "transport_relevant": false
  },
  {
    "segment_id": "S00327",
    "transport_relevant": false
  },
  {
    "segment_id": "S00328",
    "transport_relevant": true
  },
  {
    "segment_id": "S00329",
    "transport_relevant": false
  },
  {
    "segment_id": "S00330",
    "transport_relevant": false
  },
  {
    "segment_id": "S00331",
    "transport_relevant": false
  },
  {
    "segment_id": "S00332",
    "transport_relevant": false
  },
  {
    "segment_id": "S00333",
    "transport_relevant": false
  },
  {
    "segment_id": "S00334",
    "transport_relevant": true
  },
  {
    "segment_id": "S00335",
    "transport_relevant": false
  },
  {
    "segment_id": "S00336",
    "transport_relevant": false
  },
  {
    "segment_id": "S00337",
    "transport_relevant": false
  },
  {
    "segment_id": "S00338",
    "transport_relevant": false
  },
  {
    "segment_id": "S00339",
    "transport_relevant": false
  },
  {
    "segment_id": "S00340",
    "transport_relevant": false
  },
  {
    "segment_id": "S00341",
    "transport_relevant": false
  },
  {
    "segment_id": "S00342",
    "transport_relevant": false
  },
  {
    "segment_id": "S00343",
    "transport_relevant": false
  },
  {
    "segment_id": "S00344",
    "transport_relevant": true
  },
  {
    "segment_id": "S00345",
    "transport_relevant": false
  },
  {
    "segment_id": "S00346",
    "transport_relevant": false
  },
  {
    "segment_id": "S00347",
    "transport_relevant": true
  },
  {
    "segment_id": "S00348",
    "transport_relevant": false
  },
  {
    "segment_id": "S00349",
    "transport_relevant": false
  },
  {
    "segment_id": "S00350",
    "transport_relevant": false
  },
  {
    "segment_id": "S00351",
    "transport_relevant": false
  },
  {
    "segment_id": "S00352",
    "transport_relevant": false
  },
  {
    "segment_id": "S00353",
    "transport_relevant": false
  },
  {
    "segment_id": "S00354",
    "transport_relevant": false
  },
  {
    "segment_id": "S00355",
    "transport_relevant": false
  },
  {
    "segment_id": "S00356",
    "transport_relevant": false
  },
  {
    "segment_id": "S00357",
    "transport_relevant": false
  },
  {
    "segment_id": "S00358",
    "transport_relevant": false
  },
  {
    "segment_id": "S00359",
    "transport_relevant": true
  },
  {
    "segment_id": "S00360",
    "transport_relevant": true
  },
  {
    "segment_id": "S00361",
    "transport_relevant": false
  },
  {
    "segment_id": "S00362",
    "transport_relevant": false
  },
  {
    "segment_id": "S00363",
    "transport_relevant": false
  },
  {
    "segment_id": "S00364",
    "transport_relevant": false
  },
  {
    "segment_id": "S00365",
    "transport_relevant": false
  },
  {
    "segment_id": "S00366",
    "transport_relevant": false
  },
  {
    "segment_id": "S00367",
    "transport_relevant": false
  },
  {
    "segment_id": "S00368",
    "transport_relevant": false
  },
  {
    "segment_id": "S00369",
    "transport_relevant": false
  },
  {
    "segment_id": "S00370",
    "transport_relevant": false
  },
  {
    "segment_id": "S00371",
    "transport_relevant": false
  },
  {
    "segment_id": "S00372",
    "transport_relevant": false
  },
  {
    "segment_id": "S00373",
    "transport_relevant": false
  },
  {
    "segment_id": "S00374",
    "transport_relevant": false
  },
  {
    "segment_id": "S00375",
    "transport_relevant": false
  },
  {
    "segment_id": "S00376",
    "transport_relevant": false
  },
  {
    "segment_id": "S00377",
    "transport_relevant": false
  },
  {
    "segment_id": "S00378",
    "transport_relevant": false
  },
  {
    "segment_id": "S00379",
    "transport_relevant": false
  },
  {
    "segment_id": "S00380",
    "transport_relevant": false
  },
  {
    "segment_id": "S00381",
    "transport_relevant": false
  },
  {
    "segment_id": "S00382",
    "transport_relevant": false
  },
  {
    "segment_id": "S00383",
    "transport_relevant": false
  },
  {
    "segment_id": "S00384",
    "transport_relevant": false
  },
  {
    "segment_id": "S00385",
    "transport_relevant": false
  },
  {
    "segment_id": "S00386",
    "transport_relevant": false
  },
  {
    "segment_id": "S00387",
    "transport_relevant": false
  },
  {
    "segment_id": "S00388",
    "transport_relevant": false
  },
  {
    "segment_id": "S00389",
    "transport_relevant": true
  },
  {
    "segment_id": "S00390",
    "transport_relevant": true
  },
  {
    "segment_id": "S00391",
    "transport_relevant": false
  },
  {
    "segment_id": "S00392",
    "transport_relevant": false
  },
  {
    "segment_id": "S00393",
    "transport_relevant": false
  },
  {
    "segment_id": "S00394",
    "transport_relevant": false
  },
  {
    "segment_id": "S00395",
    "transport_relevant": false
  },
  {
    "segment_id": "S00396",
    "transport_relevant": false
  },
  {
    "segment_id": "S00397",
    "transport_relevant": false
  },
  {
    "segment_id": "S00398",
    "transport_relevant": true
  },
  {
    "segment_id": "S00399",
    "transport_relevant": false
  },
  {
    "segment_id": "S00400",
    "transport_relevant": false
  },
  {
    "segment_id": "S00401",
    "transport_relevant": false
  },
  {
    "segment_id": "S00402",
    "transport_relevant": false
  },
  {
    "segment_id": "S00403",
    "transport_relevant": false
  },
  {
    "segment_id": "S00404",
    "transport_relevant": false
  },
  {
    "segment_id": "S00405",
    "transport_relevant": false
  },
  {
    "segment_id": "S00406",
    "transport_relevant": false
  },
  {
    "segment_id": "S00407",
    "transport_relevant": true
  },
  {
    "segment_id": "S00408",
    "transport_relevant": true
  },
  {
    "segment_id": "S00409",
    "transport_relevant": false
  },
  {
    "segment_id": "S00410",
    "transport_relevant": false
  },
  {
    "segment_id": "S00411",
    "transport_relevant": false
  },
  {
    "segment_id": "S00412",
    "transport_relevant": false
  },
  {
    "segment_id": "S00413",
    "transport_relevant": false
  },
  {
    "segment_id": "S00414",
    "transport_relevant": false
  },
  {
    "segment_id": "S00415",
    "transport_relevant": false
  },
  {
    "segment_id": "S00416",
    "transport_relevant": false
  },
  {
    "segment_id": "S00417",
    "transport_relevant": false
  },
  {
    "segment_id": "S00418",
    "transport_relevant": false
  },
  {
    "segment_id": "S00419",
    "transport_relevant": false
  },
  {
    "segment_id": "S00420",
    "transport_relevant": false
  },
  {
    "segment_id": "S00421",
    "transport_relevant": false
  },
  {
    "segment_id": "S00422",
    "transport_relevant": false
  },
  {
    "segment_id": "S00423",
    "transport_relevant": false
  },
  {
    "segment_id": "S00424",
    "transport_relevant": false
  },
  {
    "segment_id": "S00425",
    "transport_relevant": false
  },
  {
    "segment_id": "S00426",
    "transport_relevant": false
  },
  {
    "segment_id": "S00427",
    "transport_relevant": false
  },
  {
    "segment_id": "S00428",
    "transport_relevant": false
  },
  {
    "segment_id": "S00429",
    "transport_relevant": false
  },
  {
    "segment_id": "S00430",
    "transport_relevant": false
  },
  {
    "segment_id": "S00431",
    "transport_relevant": false
  },
  {
    "segment_id": "S00432",
    "transport_relevant": false
  },
  {
    "segment_id": "S00433",
    "transport_relevant": false
  },
  {
    "segment_id": "S00434",
    "transport_relevant": true
  },
  {
    "segment_id": "S00435",
    "transport_relevant": false
  },
  {
    "segment_id": "S00436",
    "transport_relevant": false
  },
  {
    "segment_id": "S00437",
    "transport_relevant": false
  },
  {
    "segment_id": "S00438",
    "transport_relevant": false
  },
  {
    "segment_id": "S00439",
    "transport_relevant": true
  },
  {
    "segment_id": "S00440",
    "transport_relevant": true
  },
  {
    "segment_id": "S00441",
    "transport_relevant": false
  },
  {
    "segment_id": "S00442",
    "transport_relevant": false
  },
  {
    "segment_id": "S00443",
    "transport_relevant": false
  },
  {
    "segment_id": "S00444",
    "transport_relevant": false
  },
  {
    "segment_id": "S00445",
    "transport_relevant": false
  },
  {
    "segment_id": "S00446",
    "transport_relevant": true
  },
  {
    "segment_id": "S00447",
    "transport_relevant": true
  },
  {
    "segment_id": "S00448",
    "transport_relevant": false
  },
  {
    "segment_id": "S00449",
    "transport_relevant": true
  },
  {
    "segment_id": "S00450",
    "transport_relevant": false
  },
  {
    "segment_id": "S00451",
    "transport_relevant": false
  },
  {
    "segment_id": "S00452",
    "transport_relevant": false
  },
  {
    "segment_id": "S00453",
    "transport_relevant": true
  },
  {
    "segment_id": "S00454",
    "transport_relevant": true
  },
  {
    "segment_id": "S00455",
    "transport_relevant": true
  },
  {
    "segment_id": "S00456",
    "transport_relevant": true
  },
  {
    "segment_id": "S00457",
    "transport_relevant": true
  },
  {
    "segment_id": "S00458",
    "transport_relevant": true
  },
  {
    "segment_id": "S00459",
    "transport_relevant": false
  },
  {
    "segment_id": "S00460",
    "transport_relevant": false
  },
  {
    "segment_id": "S00461",
    "transport_relevant": false
  },
  {
    "segment_id": "S00462",
    "transport_relevant": false
  },
  {
    "segment_id": "S00463",
    "transport_relevant": false
  },
  {
    "segment_id": "S00464",
    "transport_relevant": false
  },
  {
    "segment_id": "S00465",
    "transport_relevant": false
  },
  {
    "segment_id": "S00466",
    "transport_relevant": false
  },
  {
    "segment_id": "S00467",
    "transport_relevant": false
  },
  {
    "segment_id": "S00468",
    "transport_relevant": false
  },
  {
    "segment_id": "S00469",
    "transport_relevant": false
  },
  {
    "segment_id": "S00470",
    "transport_relevant": false
  },
  {
    "segment_id": "S00471",
    "transport_relevant": false
  },
  {
    "segment_id": "S00472",
    "transport_relevant": false
  },
  {
    "segment_id": "S00473",
    "transport_relevant": false
  },
  {
    "segment_id": "S00474",
    "transport_relevant": false
  },
  {
    "segment_id": "S00475",
    "transport_relevant": true
  },
  {
    "segment_id": "S00476",
    "transport_relevant": false
  },
  {
    "segment_id": "S00477",
    "transport_relevant": false
  },
  {
    "segment_id": "S00478",
    "transport_relevant": false
  },
  {
    "segment_id": "S00479",
    "transport_relevant": false
  },
  {
    "segment_id": "S00480",
    "transport_relevant": false
  },
  {
    "segment_id": "S00481",
    "transport_relevant": false
  },
  {
    "segment_id": "S00482",
    "transport_relevant": false
  },
  {
    "segment_id": "S00483",
    "transport_relevant": false
  },
  {
    "segment_id": "S00484",
    "transport_relevant": false
  },
  {
    "segment_id": "S00485",
    "transport_relevant": false
  },
  {
    "segment_id": "S00486",
    "transport_relevant": false
  },
  {
    "segment_id": "S00487",
    "transport_relevant": false
  },
  {
    "segment_id": "S00488",
    "transport_relevant": false
  },
  {
    "segment_id": "S00489",
    "transport_relevant": false
  },
  {
    "segment_id": "S00490",
    "transport_relevant": false
  },
  {
    "segment_id": "S00491",
    "transport_relevant": false
  },
  {
    "segment_id": "S00492",
    "transport_relevant": false
  },
  {
    "segment_id": "S00493",
    "transport_relevant": false
  },
  {
    "segment_id": "S00494",
    "transport_relevant": false
  },
  {
    "segment_id": "S00495",
    "transport_relevant": false
  },
  {
    "segment_id": "S00496",
    "transport_relevant": false
  },
  {
    "segment_id": "S00497",
    "transport_relevant": false
  },
  {
    "segment_id": "S00498",
    "transport_relevant": true
  },
  {
    "segment_id": "S00499",
    "transport_relevant": true
  },
  {
    "segment_id": "S00500",
    "transport_relevant": true
  },
  {
    "segment_id": "S00501",
    "transport_relevant": true
  },
  {
    "segment_id": "S00502",
    "transport_relevant": true
  },
  {
    "segment_id": "S00503",
    "transport_relevant": false
  },
  {
    "segment_id": "S00504",
    "transport_relevant": false
  },
  {
    "segment_id": "S00505",
    "transport_relevant": false
  },
  {
    "segment_id": "S00506",
    "transport_relevant": true
  },
  {
    "segment_id": "S00507",
    "transport_relevant": false
  },
  {
    "segment_id": "S00508",
    "transport_relevant": true
  },
  {
    "segment_id": "S00509",
    "transport_relevant": false
  },
  {
    "segment_id": "S00510",
    "transport_relevant": false
  },
  {
    "segment_id": "S00511",
    "transport_relevant": false
  },
  {
    "segment_id": "S00512",
    "transport_relevant": true
  },
  {
    "segment_id": "S00513",
    "transport_relevant": false
  },
  {
    "segment_id": "S00514",
    "transport_relevant": true
  },
  {
    "segment_id": "S00515",
    "transport_relevant": true
  },
  {
    "segment_id": "S00516",
    "transport_relevant": false
  },
  {
    "segment_id": "S00517",
    "transport_relevant": false
  },
  {
    "segment_id": "S00518",
    "transport_relevant": false
  },
  {
    "segment_id": "S00519",
    "transport_relevant": true
  },
  {
    "segment_id": "S00520",
    "transport_relevant": true
  },
  {
    "segment_id": "S00521",
    "transport_relevant": false
  },
  {
    "segment_id": "S00522",
    "transport_relevant": false
  },
  {
    "segment_id": "S00523",
    "transport_relevant": false
  },
  {
    "segment_id": "S00524",
    "transport_relevant": false
  },
  {
    "segment_id": "S00525",
    "transport_relevant": true
  },
  {
    "segment_id": "S00526",
    "transport_relevant": false
  },
  {
    "segment_id": "S00527",
    "transport_relevant": true
  },
  {
    "segment_id": "S00528",
    "transport_relevant": true
  },
  {
    "segment_id": "S00529",
    "transport_relevant": false
  },
  {
    "segment_id": "S00530",
    "transport_relevant": false
  },
  {
    "segment_id": "S00531",
    "transport_relevant": true
  },
  {
    "segment_id": "S00532",
    "transport_relevant": false
  },
  {
    "segment_id": "S00533",
    "transport_relevant": false
  },
  {
    "segment_id": "S00534",
    "transport_relevant": false
  },
  {
    "segment_id": "S00535",
    "transport_relevant": false
  },
  {
    "segment_id": "S00536",
    "transport_relevant": false
  },
  {
    "segment_id": "S00537",
    "transport_relevant": false
  },
  {
    "segment_id": "S00538",
    "transport_relevant": false
  },
  {
    "segment_id": "S00539",
    "transport_relevant": false
  },
  {
    "segment_id": "S00540",
    "transport_relevant": false
  },
  {
    "segment_id": "S00541",
    "transport_relevant": false
  },
  {
    "segment_id": "S00542",
    "transport_relevant": false
  },
  {
    "segment_id": "S00543",
    "transport_relevant": false
  },
  {
    "segment_id": "S00544",
    "transport_relevant": false
  },
  {
    "segment_id": "S00545",
    "transport_relevant": false
  },
  {
    "segment_id": "S00546",
    "transport_relevant": false
  },
  {
    "segment_id": "S00547",
    "transport_relevant": false
  },
  {
    "segment_id": "S00548",
    "transport_relevant": false
  },
  {
    "segment_id": "S00549",
    "transport_relevant": false
  },
  {
    "segment_id": "S00550",
    "transport_relevant": false
  },
  {
    "segment_id": "S00551",
    "transport_relevant": false
  },
  {
    "segment_id": "S00552",
    "transport_relevant": false
  },
  {
    "segment_id": "S00553",
    "transport_relevant": false
  },
  {
    "segment_id": "S00554",
    "transport_relevant": false
  },
  {
    "segment_id": "S00555",
    "transport_relevant": false
  },
  {
    "segment_id": "S00556",
    "transport_relevant": false
  },
  {
    "segment_id": "S00557",
    "transport_relevant": false
  },
  {
    "segment_id": "S00558",
    "transport_relevant": false
  },
  {
    "segment_id": "S00559",
    "transport_relevant": false
  },
  {
    "segment_id": "S00560",
    "transport_relevant": false
  },
  {
    "segment_id": "S00561",
    "transport_relevant": false
  },
  {
    "segment_id": "S00562",
    "transport_relevant": false
  },
  {
    "segment_id": "S00563",
    "transport_relevant": false
  },
  {
    "segment_id": "S00564",
    "transport_relevant": false
  },
  {
    "segment_id": "S00565",
    "transport_relevant": false
  },
  {
    "segment_id": "S00566",
    "transport_relevant": false
  },
  {
    "segment_id": "S00567",
    "transport_relevant": false
  },
  {
    "segment_id": "S00568",
    "transport_relevant": false
  },
  {
    "segment_id": "S00569",
    "transport_relevant": false
  },
  {
    "segment_id": "S00570",
    "transport_relevant": false
  },
  {
    "segment_id": "S00571",
    "transport_relevant": false
  },
  {
    "segment_id": "S00572",
    "transport_relevant": false
  },
  {
    "segment_id": "S00573",
    "transport_relevant": false
  },
  {
    "segment_id": "S00574",
    "transport_relevant": false
  },
  {
    "segment_id": "S00575",
    "transport_relevant": false
  },
  {
    "segment_id": "S00576",
    "transport_relevant": false
  },
  {
    "segment_id": "S00577",
    "transport_relevant": false
  },
  {
    "segment_id": "S00578",
    "transport_relevant": false
  },
  {
    "segment_id": "S00579",
    "transport_relevant": false
  },
  {
    "segment_id": "S00580",
    "transport_relevant": false
  },
  {
    "segment_id": "S00581",
    "transport_relevant": false
  },
  {
    "segment_id": "S00582",
    "transport_relevant": false
  },
  {
    "segment_id": "S00583",
    "transport_relevant": false
  },
  {
    "segment_id": "S00584",
    "transport_relevant": false
  },
  {
    "segment_id": "S00585",
    "transport_relevant": false
  },
  {
    "segment_id": "S00586",
    "transport_relevant": false
  },
  {
    "segment_id": "S00587",
    "transport_relevant": false
  },
  {
    "segment_id": "S00588",
    "transport_relevant": false
  },
  {
    "segment_id": "S00589",
    "transport_relevant": false
  },
  {
    "segment_id": "S00590",
    "transport_relevant": false
  },
  {
    "segment_id": "S00591",
    "transport_relevant": false
  },
  {
    "segment_id": "S00592",
    "transport_relevant": false
  },
  {
    "segment_id": "S00593",
    "transport_relevant": false
  },
  {
    "segment_id": "S00594",
    "transport_relevant": false
  },
  {
    "segment_id": "S00595",
    "transport_relevant": false
  },
  {
    "segment_id": "S00596",
    "transport_relevant": false
  },
  {
    "segment_id": "S00597",
    "transport_relevant": false
  },
  {
    "segment_id": "S00598",
    "transport_relevant": false
  },
  {
    "segment_id": "S00599",
    "transport_relevant": false
  },
  {
    "segment_id": "S00600",
    "transport_relevant": false
  },
  {
    "segment_id": "S00601",
    "transport_relevant": false
  },
  {
    "segment_id": "S00602",
    "transport_relevant": false
  },
  {
    "segment_id": "S00603",
    "transport_relevant": false
  },
  {
    "segment_id": "S00604",
    "transport_relevant": false
  },
  {
    "segment_id": "S00605",
    "transport_relevant": false
  },
  {
    "segment_id": "S00606",
    "transport_relevant": false
  },
  {
    "segment_id": "S00607",
    "transport_relevant": false
  },
  {
    "segment_id": "S00608",
    "transport_relevant": false
  },
  {
    "segment_id": "S00609",
    "transport_relevant": false
  },
  {
    "segment_id": "S00610",
    "transport_relevant": false
  },
  {
    "segment_id": "S00611",
    "transport_relevant": false
  },
  {
    "segment_id": "S00612",
    "transport_relevant": false
  },
  {
    "segment_id": "S00613",
    "transport_relevant": false
  },
  {
    "segment_id": "S00614",
    "transport_relevant": false
  },
  {
    "segment_id": "S00615",
    "transport_relevant": false
  },
  {
    "segment_id": "S00616",
    "transport_relevant": false
  },
  {
    "segment_id": "S00617",
    "transport_relevant": false
  },
  {
    "segment_id": "S00618",
    "transport_relevant": false
  },
  {
    "segment_id": "S00619",
    "transport_relevant": false
  },
  {
    "segment_id": "S00620",
    "transport_relevant": false
  },
  {
    "segment_id": "S00621",
    "transport_relevant": false
  },
  {
    "segment_id": "S00622",
    "transport_relevant": false
  },
  {
    "segment_id": "S00623",
    "transport_relevant": false
  },
  {
    "segment_id": "S00624",
    "transport_relevant": false
  },
  {
    "segment_id": "S00625",
    "transport_relevant": false
  },
  {
    "segment_id": "S00626",
    "transport_relevant": false
  },
  {
    "segment_id": "S00627",
    "transport_relevant": false
  },
  {
    "segment_id": "S00628",
    "transport_relevant": false
  },
  {
    "segment_id": "S00629",
    "transport_relevant": false
  },
  {
    "segment_id": "S00630",
    "transport_relevant": true
  },
  {
    "segment_id": "S00631",
    "transport_relevant": false
  },
  {
    "segment_id": "S00632",
    "transport_relevant": false
  },
  {
    "segment_id": "S00633",
    "transport_relevant": false
  },
  {
    "segment_id": "S00634",
    "transport_relevant": false
  },
  {
    "segment_id": "S00635",
    "transport_relevant": false
  },
  {
    "segment_id": "S00636",
    "transport_relevant": false
  },
  {
    "segment_id": "S00637",
    "transport_relevant": false
  },
  {
    "segment_id": "S00638",
    "transport_relevant": false
  },
  {
    "segment_id": "S00639",
    "transport_relevant": false
  },
  {
    "segment_id": "S00640",
    "transport_relevant": false
  },
  {
    "segment_id": "S00641",
    "transport_relevant": false
  },
  {
    "segment_id": "S00642",
    "transport_relevant": false
  },
  {
    "segment_id": "S00643",
    "transport_relevant": false
  },
  {
    "segment_id": "S00644",
    "transport_relevant": false
  },
  {
    "segment_id": "S00645",
    "transport_relevant": false
  },
  {
    "segment_id": "S00646",
    "transport_relevant": false
  },
  {
    "segment_id": "S00647",
    "transport_relevant": false
  },
  {
    "segment_id": "S00648",
    "transport_relevant": false
  },
  {
    "segment_id": "S00649",
    "transport_relevant": false
  },
  {
    "segment_id": "S00650",
    "transport_relevant": false
  },
  {
    "segment_id": "S00651",
    "transport_relevant": false
  },
  {
    "segment_id": "S00652",
    "transport_relevant": false
  },
  {
    "segment_id": "S00653",
    "transport_relevant": false
  },
  {
    "segment_id": "S00654",
    "transport_relevant": false
  },
  {
    "segment_id": "S00655",
    "transport_relevant": false
  },
  {
    "segment_id": "S00656",
    "transport_relevant": false
  },
  {
    "segment_id": "S00657",
    "transport_relevant": false
  },
  {
    "segment_id": "S00658",
    "transport_relevant": false
  },
  {
    "segment_id": "S00659",
    "transport_relevant": false
  },
  {
    "segment_id": "S00660",
    "transport_relevant": false
  },
  {
    "segment_id": "S00661",
    "transport_relevant": false
  },
  {
    "segment_id": "S00662",
    "transport_relevant": false
  },
  {
    "segment_id": "S00663",
    "transport_relevant": false
  },
  {
    "segment_id": "S00664",
    "transport_relevant": false
  },
  {
    "segment_id": "S00665",
    "transport_relevant": false
  },
  {
    "segment_id": "S00666",
    "transport_relevant": false
  },
  {
    "segment_id": "S00667",
    "transport_relevant": false
  },
  {
    "segment_id": "S00668",
    "transport_relevant": false
  },
  {
    "segment_id": "S00669",
    "transport_relevant": false
  },
  {
    "segment_id": "S00670",
    "transport_relevant": false
  },
  {
    "segment_id": "S00671",
    "transport_relevant": false
  },
  {
    "segment_id": "S00672",
    "transport_relevant": false
  },
  {
    "segment_id": "S00673",
    "transport_relevant": false
  },
  {
    "segment_id": "S00674",
    "transport_relevant": false
  },
  {
    "segment_id": "S00675",
    "transport_relevant": false
  },
  {
    "segment_id": "S00676",
    "transport_relevant": false
  },
  {
    "segment_id": "S00677",
    "transport_relevant": false
  },
  {
    "segment_id": "S00678",
    "transport_relevant": false
  },
  {
    "segment_id": "S00679",
    "transport_relevant": false
  },
  {
    "segment_id": "S00680",
    "transport_relevant": false
  },
  {
    "segment_id": "S00681",
    "transport_relevant": false
  },
  {
    "segment_id": "S00682",
    "transport_relevant": false
  },
  {
    "segment_id": "S00683",
    "transport_relevant": false
  },
  {
    "segment_id": "S00684",
    "transport_relevant": false
  },
  {
    "segment_id": "S00685",
    "transport_relevant": false
  },
  {
    "segment_id": "S00686",
    "transport_relevant": false
  },
  {
    "segment_id": "S00687",
    "transport_relevant": false
  },
  {
    "segment_id": "S00688",
    "transport_relevant": false
  },
  {
    "segment_id": "S00689",
    "transport_relevant": false
  },
  {
    "segment_id": "S00690",
    "transport_relevant": false
  },
  {
    "segment_id": "S00691",
    "transport_relevant": false
  },
  {
    "segment_id": "S00692",
    "transport_relevant": false
  },
  {
    "segment_id": "S00693",
    "transport_relevant": false
  },
  {
    "segment_id": "S00694",
    "transport_relevant": false
  },
  {
    "segment_id": "S00695",
    "transport_relevant": false
  },
  {
    "segment_id": "S00696",
    "transport_relevant": false
  },
  {
    "segment_id": "S00697",
    "transport_relevant": false
  },
  {
    "segment_id": "S00698",
    "transport_relevant": false
  },
  {
    "segment_id": "S00699",
    "transport_relevant": false
  },
  {
    "segment_id": "S00700",
    "transport_relevant": false
  },
  {
    "segment_id": "S00701",
    "transport_relevant": false
  },
  {
    "segment_id": "S00702",
    "transport_relevant": false
  },
  {
    "segment_id": "S00703",
    "transport_relevant": false
  },
  {
    "segment_id": "S00704",
    "transport_relevant": false
  },
  {
    "segment_id": "S00705",
    "transport_relevant": false
  },
  {
    "segment_id": "S00706",
    "transport_relevant": false
  },
  {
    "segment_id": "S00707",
    "transport_relevant": false
  },
  {
    "segment_id": "S00708",
    "transport_relevant": false
  },
  {
    "segment_id": "S00709",
    "transport_relevant": false
  },
  {
    "segment_id": "S00710",
    "transport_relevant": false
  },
  {
    "segment_id": "S00711",
    "transport_relevant": false
  },
  {
    "segment_id": "S00712",
    "transport_relevant": false
  },
  {
    "segment_id": "S00713",
    "transport_relevant": false
  },
  {
    "segment_id": "S00714",
    "transport_relevant": false
  },
  {
    "segment_id": "S00715",
    "transport_relevant": false
  },
  {
    "segment_id": "S00716",
    "transport_relevant": false
  },
  {
    "segment_id": "S00717",
    "transport_relevant": false
  },
  {
    "segment_id": "S00718",
    "transport_relevant": false
  },
  {
    "segment_id": "S00719",
    "transport_relevant": false
  },
  {
    "segment_id": "S00720",
    "transport_relevant": false
  },
  {
    "segment_id": "S00721",
    "transport_relevant": false
  },
  {
    "segment_id": "S00722",
    "transport_relevant": false
  },
  {
    "segment_id": "S00723",
    "transport_relevant": false
  },
  {
    "segment_id": "S00724",
    "transport_relevant": false
  },
  {
    "segment_id": "S00725",
    "transport_relevant": false
  },
  {
    "segment_id": "S00726",
    "transport_relevant": false
  },
  {
    "segment_id": "S00727",
    "transport_relevant": false
  },
  {
    "segment_id": "S00728",
    "transport_relevant": false
  },
  {
    "segment_id": "S00729",
    "transport_relevant": false
  },
  {
    "segment_id": "S00730",
    "transport_relevant": false
  },
  {
    "segment_id": "S00731",
    "transport_relevant": false
  },
  {
    "segment_id": "S00732",
    "transport_relevant": false
  },
  {
    "segment_id": "S00733",
    "transport_relevant": false
  },
  {
    "segment_id": "S00734",
    "transport_relevant": false
  },
  {
    "segment_id": "S00735",
    "transport_relevant": false
  },
  {
    "segment_id": "S00736",
    "transport_relevant": false
  },
  {
    "segment_id": "S00737",
    "transport_relevant": false
  },
  {
    "segment_id": "S00738",
    "transport_relevant": false
  },
  {
    "segment_id": "S00739",
    "transport_relevant": false
  },
  {
    "segment_id": "S00740",
    "transport_relevant": false
  },
  {
    "segment_id": "S00741",
    "transport_relevant": false
  },
  {
    "segment_id": "S00742",
    "transport_relevant": false
  },
  {
    "segment_id": "S00743",
    "transport_relevant": false
  },
  {
    "segment_id": "S00744",
    "transport_relevant": false
  },
  {
    "segment_id": "S00745",
    "transport_relevant": false
  },
  {
    "segment_id": "S00746",
    "transport_relevant": false
  },
  {
    "segment_id": "S00747",
    "transport_relevant": false
  }
]